{"id":"45376518659","title":["韩国","代购","女鞋","夏","来自星星的你","同款","运动鞋","韩版","内","增高","休闲鞋","低","帮","单鞋"],"img":["https://gd1.alicdn.com/bao/uploaded/i1/TB1bGAaHFXXXXcnXVXXXXXXXXXX_!!0-item_pic.jpg","https://gd2.alicdn.com/imgextra/i2/1063685017/TB2LPIVcFXXXXcRXXXXXXXXXXXX_!!1063685017.jpg","https://gd4.alicdn.com/imgextra/i4/1063685017/TB2d_74cFXXXXbkXXXXXXXXXXXX_!!1063685017.jpg"],"attributes":[{"皮质特征":["磨砂"],"尺码":["女","36码","女","37码","女","38码","男","41码","男","43码","男","44码","女","39码","女","40码"],"适用对象":["青年（18-40周岁）"],"鞋制作工艺":["胶粘鞋"],"款式":["网面鞋"],"流行元素":["交叉绑带","防水台","网状"],"上市年份季节":["2014年秋季"],"帮面材质":["网布"],"开口深度":["深口"],"风格":["韩版"],"内里材质":["网纱"],"鞋底材质":["橡胶"],"后跟高":["低跟(1-3cm)"],"颜色分类":["浅灰色","酒红色"],"品牌":["Ollie"],"图案":["拼色"],"鞋头款式":["圆头"],"跟底款式":["内增高"],"闭合方式":["系带"]}]}