{"id":"37170370382","title":"韩剧来自星星的你全智贤千颂伊明星同款拉链玫粉皮衣朋克机车外套","img":["https://gd4.alicdn.com/bao/uploaded/i4/T1h5ewFEBaXXXXXXXX_!!0-item_pic.jpg","https://gd3.alicdn.com/imgextra/i3/691875529/T2uwzoXwhXXXXXXXXX_!!691875529.jpg","https://gd2.alicdn.com/imgextra/i2/691875529/T2VynoXtVXXXXXXXXX_!!691875529.jpg","https://gd1.alicdn.com/imgextra/i1/T1EWRSFC0hXXXXXXXX_!!0-item_pic.jpg"],"attributes":{"女装-皮衣":{"皮质":["PU"],"适用年龄":"","尺码":["XS【独家1：1定制】","S【2月25日左右出货】","M【现货！！！】","L【专柜品质】","XL【七天无理由退换】"],"制作工艺":["水洗皮"],"款式":["常规"],"流行元素":["立体装饰","拉链"],"领子":"","服装版型":["修身"],"年份/季节":"","袖长":["长袖"],"组合形式":"","袖型":["常规"],"风格":["通勤"],"category":"[女装-皮衣, 女装-外套, 女装-上衣, 女装, 服装]","厚薄":"","年份季节":"","货号":["KUG73"],"颜色分类":["内搭白T","原版枚粉色现货"],"衣长":"","衣门襟":["拉链"],"品牌":["KGR39h"],"领型":["POLO领"],"图案":"","面料":""}}}