{"id":"37191781566","title":"代购 巴黎代购 YSL SLP 全智贤 来自星星的你 同款包","img":["https://gd1.alicdn.com/bao/uploaded/i1/T1KoBUFDxDXXXXXXXX_!!0-item_pic.jpg","https://gd1.alicdn.com/imgextra/i1/67300094/T2gFW6XyXaXXXXXXXX_!!67300094.jpg","https://gd3.alicdn.com/imgextra/i3/67300094/T2HCy7XrxXXXXXXXXX_!!67300094.jpg"],"attributes":{"通用-手提包":{"肩带样式":"","大小":"","适用对象":"","款式":["单肩包"],"皮革材质":["头层牛皮"],"成色":"","风格":"","是否可折叠":"","里料材质":"","流行款式名称":"","颜色分类":["白色","黑色"],"货号":"","箱包硬度":"","图案":"","材质工艺":"","闭合方式":"","质地":["牛皮"],"内部结构":"","形状":"","流行元素":"","防水程度":"","提拎部件类型":"","有无夹层":"","背包方式":["单肩手提"],"category":"[通用-手提包, 通用, 箱包]","箱包外袋种类":"","品牌":"","适用场景":""},"男包-商务包":{"肩带样式":"","大小":"","适用对象":"","拿包方式":"","款式":["单肩包"],"成色":"","皮革材质":["头层牛皮"],"风格":"","性别":"","是否可折叠":"","里料材质":"","颜色分类":["白色","黑色"],"货号":"","箱包硬度":"","图案":"","材质工艺":"","闭合方式":"","皮质特征":"","质地":["牛皮"],"容纳电脑尺寸":"","箱包尺寸":"","折数":"","流行元素":"","形状":"","内部结构":"","防水程度":"","提拎部件类型":"","是否有背部缓冲棉":"","有无夹层":"","背包方式":["单肩手提"],"category":"[男包-商务包, 男包, 箱包]","箱包外袋种类":"","品牌":"","适用场景":""},"女包-单肩包":{"肩带样式":"","大小":"","适用对象":"","款式":["单肩包"],"皮革材质":["头层牛皮"],"成色":"","风格":"","是否可折叠":"","里料材质":"","流行款式名称":"","颜色分类":["白色","黑色"],"货号":"","箱包硬度":"","图案":"","材质工艺":"","闭合方式":"","质地":["牛皮"],"内部结构":"","形状":"","流行元素":"","提拎部件类型":"","有无夹层":"","背包方式":["单肩手提"],"category":"[女包-单肩包, 女包, 箱包]","箱包外袋种类":"","品牌":"","适用场景":""},"女包-手提包":{"肩带样式":"","大小":"","适用对象":"","款式":["单肩包"],"皮革材质":["头层牛皮"],"成色":"","风格":"","是否可折叠":"","里料材质":"","流行款式名称":"","颜色分类":["白色","黑色"],"货号":"","箱包硬度":"","图案":"","材质工艺":"","闭合方式":"","质地":["牛皮"],"内部结构":"","流行元素":"","形状":"","提拎部件类型":"","有无夹层":"","背包方式":["单肩手提"],"category":"[女包-手提包, 女包, 箱包]","箱包外袋种类":"","品牌":"","适用场景":""},"通用-斜挎包":{"肩带样式":"","大小":"","适用对象":"","款式":["单肩包"],"皮革材质":["头层牛皮"],"成色":"","风格":"","是否可折叠":"","里料材质":"","流行款式名称":"","颜色分类":["白色","黑色"],"货号":"","箱包硬度":"","图案":"","材质工艺":"","闭合方式":"","质地":["牛皮"],"内部结构":"","形状":"","流行元素":"","提拎部件类型":"","有无夹层":"","背包方式":["单肩手提"],"category":"[通用-斜挎包, 通用, 箱包]","箱包外袋种类":"","品牌":"","适用场景":""},"女包-商务包":{"肩带样式":"","大小":"","适用对象":"","款式":["单肩包"],"皮革材质":["头层牛皮"],"成色":"","风格":"","是否可折叠":"","性别":"","里料材质":"","流行款式名称":"","颜色分类":["白色","黑色"],"货号":"","箱包硬度":"","图案":"","材质工艺":"","闭合方式":"","质地":["牛皮"],"容纳电脑尺寸":"","箱包尺寸":"","内部结构":"","流行元素":"","形状":"","防水程度":"","提拎部件类型":"","有无夹层":"","是否有背部缓冲棉":"","背包方式":["单肩手提"],"category":"[女包-商务包, 女包, 箱包]","箱包外袋种类":"","品牌":"","适用场景":""},"男包-手提包":{"肩带样式":"","大小":"","适用对象":"","款式":["单肩包"],"成色":"","皮革材质":["头层牛皮"],"风格":"","性别":"","旅行袋类型":"","有无拉杆":"","包袋大小":"","是否可折叠":"","里料材质":"","颜色分类":["白色","黑色"],"货号":"","箱包硬度":"","图案":"","材质工艺":"","闭合方式":"","质地":["牛皮"],"容纳电脑尺寸":"","内部结构":"","流行元素":"","形状":"","提拎部件类型":"","有无夹层":"","背包方式":["单肩手提"],"category":"[男包-手提包, 男包, 箱包]","箱包外袋种类":"","品牌":"","适用场景":""},"男包-休闲包":{"肩带样式":"","大小":"","适用对象":"","款式":["单肩包"],"皮革材质":["头层牛皮"],"成色":"","风格":"","性别":"","是否可折叠":"","里料材质":"","颜色分类":["白色","黑色"],"货号":"","箱包硬度":"","图案":"","材质工艺":"","闭合方式":"","质地":["牛皮"],"容纳电脑尺寸":"","箱包尺寸":"","内部结构":"","形状":"","流行元素":"","防水程度":"","提拎部件类型":"","是否有背部缓冲棉":"","有无夹层":"","背包方式":["单肩手提"],"category":"[男包-休闲包, 男包, 箱包]","箱包外袋种类":"","品牌":"","适用场景":""},"通用-商务包":{"肩带样式":"","大小":"","适用对象":"","款式":["单肩包"],"皮革材质":["头层牛皮"],"成色":"","风格":"","是否可折叠":"","里料材质":"","货号":"","颜色分类":["白色","黑色"],"箱包硬度":"","图案":"","闭合方式":"","质地":["牛皮"],"容纳电脑尺寸":"","箱包尺寸":"","内部结构":"","形状":"","流行元素":"","防水程度":"","提拎部件类型":"","是否有背部缓冲棉":"","有无夹层":"","背包方式":["单肩手提"],"category":"[通用-商务包, 通用, 箱包]","箱包外袋种类":"","品牌":"","适用场景":""},"女包-休闲包":{"肩带样式":"","大小":"","适用对象":"","款式":["单肩包"],"皮革材质":["头层牛皮"],"成色":"","风格":"","是否可折叠":"","性别":"","里料材质":"","流行款式名称":"","颜色分类":["白色","黑色"],"货号":"","箱包硬度":"","图案":"","材质工艺":"","闭合方式":"","容纳电脑尺寸":"","质地":["牛皮"],"箱包尺寸":"","流行元素":"","形状":"","内部结构":"","防水程度":"","提拎部件类型":"","是否有背部缓冲棉":"","有无夹层":"","背包方式":["单肩手提"],"category":"[女包-休闲包, 女包, 箱包]","箱包外袋种类":"","品牌":"","适用场景":""},"女包-斜挎包":{"肩带样式":"","大小":"","适用对象":"","款式":["单肩包"],"皮革材质":["头层牛皮"],"成色":"","风格":"","是否可折叠":"","里料材质":"","流行款式名称":"","颜色分类":["白色","黑色"],"货号":"","箱包硬度":"","图案":"","材质工艺":"","闭合方式":"","质地":["牛皮"],"内部结构":"","形状":"","流行元素":"","提拎部件类型":"","有无夹层":"","背包方式":["单肩手提"],"category":"[女包-斜挎包, 女包, 箱包]","箱包外袋种类":"","品牌":"","适用场景":""},"男包-单肩包":{"肩带样式":"","大小":"","适用对象":"","款式":["单肩包"],"皮革材质":["头层牛皮"],"成色":"","风格":"","是否可折叠":"","里料材质":"","颜色分类":["白色","黑色"],"货号":"","箱包硬度":"","图案":"","材质工艺":"","闭合方式":"","质地":["牛皮"],"容纳电脑尺寸":"","内部结构":"","形状":"","流行元素":"","提拎部件类型":"","有无夹层":"","背包方式":["单肩手提"],"category":"[男包-单肩包, 男包, 箱包]","箱包外袋种类":"","品牌":"","适用场景":""},"通用-手拿包":{"肩带样式":"","大小":"","适用对象":"","拿包方式":"","款式":["单肩包"],"成色":"","皮革材质":["头层牛皮"],"风格":"","是否可折叠":"","里料材质":"","流行款式名称":"","颜色分类":["白色","黑色"],"货号":"","箱包硬度":"","图案":"","材质工艺":"","闭合方式":"","皮质特征":"","质地":["牛皮"],"流行元素":"","形状":"","内部结构":"","提拎部件类型":"","有无夹层":"","背包方式":["单肩手提"],"category":"[通用-手拿包, 通用, 箱包]","箱包外袋种类":"","品牌":"","适用场景":""}}}