{"id":"44435898630","title":["来自星星的你","同款","女单鞋","春夏","新款","真皮","尖头","浅","口","闪","钻","细","跟","高跟鞋","包邮"],"img":["https://gd3.alicdn.com/bao/uploaded/i3/TB1keDVHpXXXXbcXVXXXXXXXXXX_!!0-item_pic.jpg","https://gd2.alicdn.com/imgextra/i2/122584229/TB2vknUcXXXXXbCXpXXXXXXXXXX_!!122584229.jpg","https://gd2.alicdn.com/imgextra/i2/122584229/TB20Ez6cXXXXXXxXXXXXXXXXXXX_!!122584229.jpg"],"attributes":[{"尺码":["33","34","35","36","37","38","39","40"],"适用对象":["青年（18-40周岁）"],"鞋制作工艺":["胶粘鞋"],"款式":["懒人鞋"],"流行元素":["浅口","亮片"],"上市年份季节":["2015年春季"],"鞋垫材质":["羊皮"],"帮面材质":["亮片布"],"开口深度":["浅口"],"风格":["韩版"],"内里材质":["羊皮"],"鞋底材质":["橡胶"],"后跟高":["高跟(5-8cm)"],"颜色分类":["中跟","-","7.5cm","高跟","-","10cm"],"货号":["CC38"],"图案":["纯色"],"适用场景":["日常"],"鞋头款式":["尖头"],"跟底款式":["细跟"],"闭合方式":["套脚"]}]}