{"id":"523800380127","title":"全智贤千颂伊来自星星的你同款外套杨幂霍思燕棉衣女 mr mrs furs","img":["https://gd2.alicdn.com/bao/uploaded/i2/TB1krTVKXXXXXbdXVXXXXXXXXXX_!!0-item_pic.jpg","https://gd3.alicdn.com/imgextra/i3/7352/TB2ZrOkgFXXXXcjXpXXXXXXXXXX_!!7352.jpg","https://gd2.alicdn.com/imgextra/i2/7352/TB292yngFXXXXa4XpXXXXXXXXXX_!!7352.jpg","https://gd4.alicdn.com/imgextra/i4/7352/TB2nf9sgFXXXXXAXpXXXXXXXXXX_!!7352.jpg","https://gd3.alicdn.com/imgextra/i3/7352/TB2h69JgFXXXXXIXXXXXXXXXXXX_!!7352.jpg"],"attributes":{"女装-棉服棉衣":{"适用年龄":["25-29周岁"],"流行元素/工艺":["带毛领","口袋","绑带","钉珠","亮片","纽扣","拉链"],"尺码":["XS","S","M","L","XL","2XL"],"通勤":["韩版"],"领子":["连帽"],"成分含量":["91%(含)-95%(含)"],"大码女装分类":"","服装版型":["直筒"],"年份/季节":["2015年冬季"],"街头":"","袖长":["长袖"],"组合形式":"","袖型":["常规"],"风格":["通勤"],"category":"[女装-棉服棉衣, 女装-外套, 女装-上衣, 女装, 服装]","甜美":"","厚薄":["加厚"],"填充物":["棉96%及以上"],"货号":["Mr","&","Mrs","Furs170"],"颜色分类":["玫红色","蓝色"],"衣长":["短款"],"品牌":["Guimeigongzhu/鬼魅公主"],"衣门襟":["拉链"],"图案":["纯色"],"面料材质":["棉"]}}}