{"id":"524113263513","title":"来自星星的你千颂伊同款雪地靴 羊皮毛一体棉拖鞋女 保暖家居鞋冬","img":["https://gd2.alicdn.com/bao/uploaded/i2/TB1cBAqKXXXXXXfXpXXXXXXXXXX_!!0-item_pic.jpg","https://gd1.alicdn.com/imgextra/i1/2628742475/TB2oy0xhXXXXXXAXpXXXXXXXXXX_!!2628742475.jpg","https://gd4.alicdn.com/imgextra/i4/2628742475/TB20WFvhXXXXXa0XpXXXXXXXXXX_!!2628742475.jpg"],"attributes":{"女鞋-棉拖":{"适用季节":"","尺码":["35","36","37","38","39","40","41","42","43","44"],"适合场合":"","适用对象":"","鞋制作工艺":["胶粘鞋"],"款式":["板鞋"],"包装体积":"","上市年份季节":["2015年秋季"],"鞋垫材质":"","型号":"","帮面材质":["头层牛皮"],"风格":["韩版"],"category":"[女鞋-棉拖, 女鞋, 鞋靴]","鞋底材质":["橡胶发泡"],"里料材质":"","毛重":"","后跟高":["平跟(小于等于1cm)"],"货号":"","颜色分类":["灰色","黑色"],"品牌":"","图案":["豹纹"],"跟底款式":["平底"]}}}