{"id":"524186443029","title":"来自星星的你千颂伊同款军绿色棉衣超大白毛领加厚短款棉服外套女","img":["https://gd2.alicdn.com/bao/uploaded/i2/T1OKdYFCNhXXXXXXXX_!!0-item_pic.jpg"],"attributes":{"女装-棉服棉衣":{"适用年龄":"","流行元素/工艺":["口袋"],"尺码":["S","M","L","XL"],"通勤":["韩版"],"领子":["POLO领"],"成分含量":"","大码女装分类":"","服装版型":["修身"],"年份/季节":"","街头":"","袖长":["长袖"],"组合形式":"","袖型":["常规"],"风格":["通勤"],"category":"[女装-棉服棉衣, 女装-外套, 女装-上衣, 女装, 服装]","甜美":"","厚薄":"","填充物":"","货号":["556254479-22"],"颜色分类":["图片色","专柜代购附小票","七天无理由换号"],"衣长":["中长款"],"品牌":["sssssssssszzzzzzzzzzz"],"衣门襟":["双排扣"],"图案":["纯色"],"面料材质":["羊毛"]}}}