{"id":"525002927387","title":"来自星星的你同款狐狸毛内胆皮草貉子毛领牛仔外套女短款可脱卸","img":["https://gd1.alicdn.com/bao/uploaded/i5/TB1.8yyLXXXXXc.XXXXYXGcGpXX_M2.SS2_50x50.jpg","https://gd1.alicdn.com/imgextra/i5/TB1TLKsLXXXXXbwXpXXYXGcGpXX_M2.SS2_50x50.jpg","https://gd1.alicdn.com/imgextra/i7/TB1zZN4LXXXXXXRapXXYXGcGpXX_M2.SS2_50x50.jpg","https://gd3.alicdn.com/imgextra/i3/2633532614/TB2ihw6iFXXXXbNXXXXXXXXXXXX_!!2633532614.jpg","https://gd1.alicdn.com/imgextra/i3/TB1qY2gLXXXXXXKapXXYXGcGpXX_M2.SS2_50x50.jpg","https://gd4.alicdn.com/imgextra/i4/TB1EvV5LXXXXXXTXVXXXXXXXXXX_!!0-item_pic.jpg"],"attributes":{"女装-毛呢外套":{"尺码":["M(正版版型)","XL(赠送运费险)","S(拉链脱卸)","L(质量保证)"],"流行元素/工艺":"","上市年份季节":"","大码女装分类":"","组合形式":"","风格":["通勤"],"甜美":"","里料材质":"","年份季节":"","厚薄":"","颜色分类":["牛仔+枚红内胆","牛仔+蓝色内胆","牛仔+白色内胆","牛仔+猪猪粉内胆"],"货号":["DZ0452"],"服装款式细节":"","服饰工艺":"","衣门襟":["拉链"],"衣长":["短款"],"领型":["方领"],"面料主材质含量":"","图案":"","面料材质":["其他"],"面料":"","适用年龄":["25-29周岁"],"穿着方式":"","通勤":["韩版"],"领子":"","成分含量":"","服装版型":"","街头":"","袖长":["长袖"],"袖型":["常规"],"category":"[女装-毛呢外套, 女装-外套, 女装-上衣, 女装, 服装]","里料图案":"","品牌":["DZZD"]}}}